libjpeg/__init__.py
libjpeg/_libjpeg.cpp
libjpeg/_libjpeg.pyx
libjpeg/_version.py
libjpeg/py.typed
libjpeg/tests/__init__.py
libjpeg/tests/README.rst
libjpeg/tests/test_decode.py
libjpeg/tests/test_handler.py
libjpeg/tests/test_parameters.py
libjpeg/utils.py
_libjpeg.cp311-win_amd64.pyd
pylibjpeg_libjpeg-2.1.1.dist-info/entry_points.txt
pylibjpeg_libjpeg-2.1.1.dist-info/LICENSE
pylibjpeg_libjpeg-2.1.1.dist-info/METADATA
pylibjpeg_libjpeg-2.1.1.dist-info/WHEEL
pylibjpeg_libjpeg-2.1.1.dist-info/RECORD
