Metadata-Version: 2.1
Name: pylibjpeg-libjpeg
Version: 2.1.1
Summary: A Python wrapper for libjpeg, with a focus on use as a plugin for for pylibjpeg
Home-page: https://github.com/pydicom/pylibjpeg-libjpeg
License: GPL V3.0
Keywords: dicom pydicom python jpg jpeg jpg-ls jpeg-ls libjpeg pylibjpeg
Author: pylibjpeg-libjpeg contributors
Maintainer: scaramallion
Maintainer-email: scaramallion@users.noreply.github.com
Requires-Python: >=3.8,<4.0
Classifier: Development Status :: 5 - Production/Stable
Classifier: Intended Audience :: Developers
Classifier: Intended Audience :: Healthcare Industry
Classifier: Intended Audience :: Science/Research
Classifier: License :: OSI Approved :: GNU General Public License v3 (GPLv3)
Classifier: License :: Other/Proprietary License
Classifier: Natural Language :: English
Classifier: Operating System :: MacOS :: MacOS X
Classifier: Operating System :: Microsoft :: Windows
Classifier: Operating System :: POSIX :: Linux
Classifier: Programming Language :: C++
Classifier: Programming Language :: Python :: 3
Classifier: Programming Language :: Python :: 3.8
Classifier: Programming Language :: Python :: 3.9
Classifier: Programming Language :: Python :: 3.10
Classifier: Programming Language :: Python :: 3.11
Classifier: Programming Language :: Python :: 3.12
Classifier: Topic :: Scientific/Engineering :: Medical Science Apps.
Classifier: Topic :: Software Development :: Libraries
Requires-Dist: numpy
